biquaternions/__init__.py
biquaternions/biquaternions.py
biquaternions-0.0.2.dist-info/LICENSE
biquaternions-0.0.2.dist-info/METADATA
biquaternions-0.0.2.dist-info/WHEEL
biquaternions-0.0.2.dist-info/top_level.txt
biquaternions-0.0.2.dist-info/RECORD
